Metadata-Version: 1.1
Name: telega-compose
Version: 0.0.1
Summary: Utility to render docker-compose files with different states
Home-page: https://github.com/django-stars/telega-compose
Author: Django Stars
Author-email: alexander.ryabtsev@djangostars.com
License: MIT
Platform: UNKNOWN
Classifier: Development Status :: 3 - Alpha
Classifier: Environment :: Console
Classifier: Intended Audience :: Developers
Classifier: License :: OSI Approved :: MIT License
Classifier: Natural Language :: English
Classifier: Operating System :: OS Independent
Classifier: Programming Language :: Python
Classifier: Programming Language :: Python :: 3
Classifier: Programming Language :: Python :: 3.6
Classifier: Topic :: Utilities
